{
  "name": "Go-UPC Barcode-Lookup API",
  "description": "Find information on products from around the globe. The API supports UPC, EAN, and ISBN barcode numbers, and info returned includes product name, description, brand, image URL, and more.",
  "categories": [],
  "region": null,
  "logo": "logo.png",
  "openApiJsonUrl": "https://api.apis.guru/v2/specs/go-upc.com/1.0.0/openapi.json",
  "openApiYamlUrl": "https://api.apis.guru/v2/specs/go-upc.com/1.0.0/openapi.yaml",
  "openApiVersion": "3.0.0",
  "externalDocsUrl": null,
  "source": "apis.guru"
}
