{
  "name": "MySQLManagementClient",
  "description": "The Microsoft Azure management API provides create, read, update, and delete functionality for Azure MySQL resources including servers, databases, firewall rules, VNET rules, log files and configurations with new business model.",
  "categories": [
    "cloud"
  ],
  "logo": "logo.png",
  "openApiJsonUrl": "https://api.apis.guru/v2/specs/azure.com/mysql/2017-12-01-preview/swagger.json",
  "openApiYamlUrl": "https://api.apis.guru/v2/specs/azure.com/mysql/2017-12-01-preview/swagger.yaml",
  "openApiVersion": "2.0",
  "externalDocsUrl": null,
  "source": "apis.guru"
}