{
  "name": "SearchIndexClient",
  "description": "Client that can be used to query an index and upload, merge, or delete documents.",
  "categories": [
    "cloud"
  ],
  "region": null,
  "logo": "logo.png",
  "openApiJsonUrl": "https://api.apis.guru/v2/specs/azure.com/search-searchindex/2019-05-06-Preview/swagger.json",
  "openApiYamlUrl": "https://api.apis.guru/v2/specs/azure.com/search-searchindex/2019-05-06-Preview/swagger.yaml",
  "openApiVersion": "2.0",
  "externalDocsUrl": null,
  "source": "apis.guru"
}
